{
  "id": "snippet-016",
  "title": "Builder Pattern - Step-by-Step Object Construction",
  "language": "javascript",
  "tags": ["javascript", "design-patterns", "builder", "creational", "fluent-api"],
  "codeFile": "snippet-016.js",
  "notes": "Builder constructs complex objects step by step. Methods return 'this' for chaining (fluent interface). Use when: many optional parameters, readable configuration, need validation between steps. Common in query builders, HTTP clients, configuration.",
  "dateAdded": "2026-01-16T14:30:00Z",
  "category": "Design Patterns - Creational"
}
